fivedreg/__init__.py
fivedreg/version.py
fivedreg/data/__init__.py
fivedreg/data/dataloader.py
fivedreg/neural_network/NN.py
fivedreg/neural_network/__init__.py
fivedreg-0.0.6.dist-info/licenses/LICENSE
fivedreg-0.0.6.dist-info/METADATA
fivedreg-0.0.6.dist-info/WHEEL
fivedreg-0.0.6.dist-info/top_level.txt
fivedreg-0.0.6.dist-info/RECORD
