Metadata-Version: 2.4
Name: fivedreg
Version: 0.0.6
Summary: A lightweight, configurable neural network for 5D interpolation.
Author-email: Rowan d'Auria <rd761@cam.ac.uk>
Project-URL: Homepage, https://github.com/rowan-dauria/c1-coursework
Classifier: Development Status :: 5 - Production/Stable
Classifier: Programming Language :: Python :: 3
Classifier: License :: OSI Approved :: MIT License
Classifier: Operating System :: OS Independent
Requires-Python: >=3.12
License-File: LICENSE
Requires-Dist: tensorflow<3.0.0,>=2.10.0
Requires-Dist: numpy>=1.21.0
Requires-Dist: pandas>=1.21.0
Provides-Extra: dev
Requires-Dist: build>=0.10.0; extra == "dev"
Requires-Dist: twine>=4.0.0; extra == "dev"
Requires-Dist: pytest>=7.0.0; extra == "dev"
Dynamic: license-file
